hotjax/__init__.py
hotjax/__main__.py
hotjax/base.py
hotjax/cli.py
hotjax-0.0.1.dist-info/LICENSE
hotjax-0.0.1.dist-info/METADATA
hotjax-0.0.1.dist-info/WHEEL
hotjax-0.0.1.dist-info/entry_points.txt
hotjax-0.0.1.dist-info/top_level.txt
hotjax-0.0.1.dist-info/RECORD
