Metadata-Version: 2.1
Name: hotjax
Version: 0.0.1
Summary: Probabilistic Machine Learning with Energy-Based Models in JAX
Home-page: https://github.com/amirabbasasadi/hotjax/
Author: amirabbasasadi
License-File: LICENSE
Provides-Extra: test
Requires-Dist: pytest ; extra == 'test'
Requires-Dist: coverage ; extra == 'test'
Requires-Dist: flake8 ; extra == 'test'
Requires-Dist: black ; extra == 'test'
Requires-Dist: isort ; extra == 'test'
Requires-Dist: pytest-cov ; extra == 'test'
Requires-Dist: mypy ; extra == 'test'
Requires-Dist: gitchangelog ; extra == 'test'
Requires-Dist: mkdocs ; extra == 'test'
